Metadata-Version: 2.4
Name: adafruit-circuitpython-bitbangio
Version: 1.3.20
Summary: A library for adding bitbang I2C and SPI to CircuitPython without the built-in bitbangio module
Author-email: Adafruit Industries <circuitpython@adafruit.com>
License: MIT
Project-URL: Homepage, https://github.com/adafruit/Adafruit_CircuitPython_BitbangIO
Keywords: adafruit,blinka,circuitpython,micropython,bitbangio,bitbang,spi,i2c,software
Classifier: Intended Audience :: Developers
Classifier: Topic :: Software Development :: Libraries
Classifier: Topic :: Software Development :: Embedded Systems
Classifier: Topic :: System :: Hardware
Classifier: License :: OSI Approved :: MIT License
Classifier: Programming Language :: Python :: 3
License-File: LICENSE
Requires-Dist: Adafruit-Blinka
Requires-Dist: typing-extensions~=4.0
Provides-Extra: optional
Dynamic: license-file
